NightingaleORM/__init__.py
NightingaleORM/dbmodel.py
NightingaleORM/fields.py
NightingaleORM/pgsqlInterpreter.py
Nightingale_ORM-0.9.23.dist-info/METADATA
Nightingale_ORM-0.9.23.dist-info/WHEEL
Nightingale_ORM-0.9.23.dist-info/top_level.txt
Nightingale_ORM-0.9.23.dist-info/RECORD
